mcp_azure_billing/__init__.py
mcp_azure_billing/server.py
mcp_azure_billing-0.0.3.dist-info/METADATA
mcp_azure_billing-0.0.3.dist-info/WHEEL
mcp_azure_billing-0.0.3.dist-info/entry_points.txt
mcp_azure_billing-0.0.3.dist-info/top_level.txt
mcp_azure_billing-0.0.3.dist-info/RECORD
