Metadata-Version: 2.4
Name: mcp-azure-billing
Version: 0.0.3
Summary: MCP server for Azure Billing integration
Project-URL: Homepage, https://github.com/yourusername/mcp-azure-billing
Project-URL: Bug Tracker, https://github.com/yourusername/mcp-azure-billing/issues
Requires-Python: >=3.10
Requires-Dist: mcp[cli]>=1.6.0
Requires-Dist: httpx>=0.24.0
